stix_shifter_modules/trendmicro_vision_one/__init__.py
stix_shifter_modules/trendmicro_vision_one/entry_point.py
stix_shifter_modules/trendmicro_vision_one/configuration/config.json
stix_shifter_modules/trendmicro_vision_one/configuration/dialects.json
stix_shifter_modules/trendmicro_vision_one/configuration/lang_en.json
stix_shifter_modules/trendmicro_vision_one/stix_translation/__init__.py
stix_shifter_modules/trendmicro_vision_one/stix_translation/json_to_stix_translator.py
stix_shifter_modules/trendmicro_vision_one/stix_translation/query_constructor.py
stix_shifter_modules/trendmicro_vision_one/stix_translation/query_translator.py
stix_shifter_modules/trendmicro_vision_one/stix_translation/transformers.py
stix_shifter_modules/trendmicro_vision_one/stix_translation/visionone_util.py
stix_shifter_modules/trendmicro_vision_one/stix_translation/json/endpointActivityData_from_stix_map.json
stix_shifter_modules/trendmicro_vision_one/stix_translation/json/messageActivityData_from_stix_map.json
stix_shifter_modules/trendmicro_vision_one/stix_translation/json/operators.json
stix_shifter_modules/trendmicro_vision_one/stix_translation/json/to_stix_map.json
stix_shifter_modules/trendmicro_vision_one/stix_translation/json/stix_2_1/endpointActivityData_from_stix_map.json
stix_shifter_modules/trendmicro_vision_one/stix_translation/json/stix_2_1/messageActivityData_from_stix_map.json
stix_shifter_modules/trendmicro_vision_one/stix_translation/json/stix_2_1/to_stix_map.json
stix_shifter_modules/trendmicro_vision_one/stix_transmission/__init__.py
stix_shifter_modules/trendmicro_vision_one/stix_transmission/api_client.py
stix_shifter_modules/trendmicro_vision_one/stix_transmission/delete_connector.py
stix_shifter_modules/trendmicro_vision_one/stix_transmission/error_mapper.py
stix_shifter_modules/trendmicro_vision_one/stix_transmission/ping_connector.py
stix_shifter_modules/trendmicro_vision_one/stix_transmission/query_connector.py
stix_shifter_modules_trendmicro_vision_one-8.0.2.dist-info/licenses/AUTHORS.md
stix_shifter_modules_trendmicro_vision_one-8.0.2.dist-info/licenses/LICENSE.md
stix_shifter_modules_trendmicro_vision_one-8.0.2.dist-info/licenses/NOTICE
stix_shifter_modules_trendmicro_vision_one-8.0.2.dist-info/METADATA
stix_shifter_modules_trendmicro_vision_one-8.0.2.dist-info/WHEEL
stix_shifter_modules_trendmicro_vision_one-8.0.2.dist-info/top_level.txt
stix_shifter_modules_trendmicro_vision_one-8.0.2.dist-info/RECORD
